drawio_svg_library/__about__.py
drawio_svg_library/__init__.py
drawio_svg_library/cli.py
drawio_svg_library/core.py
drawio_svg_library-0.0.1.dist-info/METADATA
drawio_svg_library-0.0.1.dist-info/WHEEL
drawio_svg_library-0.0.1.dist-info/entry_points.txt
drawio_svg_library-0.0.1.dist-info/licenses/LICENSE.txt
drawio_svg_library-0.0.1.dist-info/RECORD
