Metadata-Version: 2.1
Name: drawio-svg-library
Version: 0.0.1
Summary: Generate draw.io libraries from SVGs
Project-URL: Documentation, https://github.com/LukasPatzke/drawio-svg-library#readme
Project-URL: Issues, https://github.com/LukasPatzke/drawio-svg-library/issues
Project-URL: Source, https://github.com/LukasPatzke/drawio-svg-library
Author-email: Lukas Patzke <lukas@patzke.me>
License-File: LICENSE.txt
Classifier: Development Status :: 4 - Beta
Classifier: Programming Language :: Python
Classifier: Programming Language :: Python :: 3.7
Classifier: Programming Language :: Python :: 3.8
Classifier: Programming Language :: Python :: 3.9
Classifier: Programming Language :: Python :: 3.10
Classifier: Programming Language :: Python :: 3.11
Classifier: Programming Language :: Python :: Implementation :: CPython
Classifier: Programming Language :: Python :: Implementation :: PyPy
Requires-Python: >=3.7
Requires-Dist: typer[all]~=0.7
